COPYING
MANIFEST.in
README.rst
fusha.py
setup.py
fusha.egg-info/PKG-INFO
fusha.egg-info/SOURCES.txt
fusha.egg-info/dependency_links.txt
fusha.egg-info/top_level.txt