Metadata-Version: 1.0
Name: fusha
Version: 0.1
Summary: Easily customizable progress bar module
Home-page: https://github.com/kenkov/fusha
Author: Noriyuki Abe
Author-email: kenko.py@gmail.com
License: MIT License
Platform: UNKNOWN
